MANIFEST.in
README.rst
setup.py
docs/conf.py
docs/index.rst
xbob/__init__.py
xbob.db.caspeal.egg-info/PKG-INFO
xbob.db.caspeal.egg-info/SOURCES.txt
xbob.db.caspeal.egg-info/dependency_links.txt
xbob.db.caspeal.egg-info/entry_points.txt
xbob.db.caspeal.egg-info/namespace_packages.txt
xbob.db.caspeal.egg-info/not-zip-safe
xbob.db.caspeal.egg-info/requires.txt
xbob.db.caspeal.egg-info/top_level.txt
xbob/db/__init__.py
xbob/db/caspeal/__init__.py
xbob/db/caspeal/create.py
xbob/db/caspeal/db.sql3
xbob/db/caspeal/driver.py
xbob/db/caspeal/models.py
xbob/db/caspeal/query.py
xbob/db/caspeal/test.py