Metadata-Version: 1.1
Name: xbob.db.caspeal
Version: 1.0.3
Summary: CAS-PEAL Database Access API for Bob
Home-page: http://github.com/bioidiap/xbob.db.caspeal
Author: Manuel Guenther
Author-email: manuel.guenther@idiap.ch
License: GPLv3
Platform: UNKNOWN
Classifier: Development Status :: 4 - Beta
Classifier: Intended Audience :: Developers
Classifier: License :: OSI Approved :: GNU General Public License v3 (GPLv3)
Classifier: Natural Language :: English
Classifier: Programming Language :: Python
Classifier: Topic :: Scientific/Engineering :: Artificial Intelligence
Classifier: Topic :: Database :: Front-Ends
